smart_diagnostics_client/__init__.py
smart_diagnostics_client/api_client.py
smart_diagnostics_client/configuration.py
smart_diagnostics_client/rest.py
smart_diagnostics_client/api/__init__.py
smart_diagnostics_client/api/activity_events_api.py
smart_diagnostics_client/api/alerts_api.py
smart_diagnostics_client/api/analytics_api.py
smart_diagnostics_client/api/assets_api.py
smart_diagnostics_client/api/base_stations_api.py
smart_diagnostics_client/api/bearings_api.py
smart_diagnostics_client/api/board_ticket_statuses_api.py
smart_diagnostics_client/api/board_tickets_api.py
smart_diagnostics_client/api/bulletins_api.py
smart_diagnostics_client/api/corporations_api.py
smart_diagnostics_client/api/dashboards_api.py
smart_diagnostics_client/api/documents_api.py
smart_diagnostics_client/api/edge_compute_api.py
smart_diagnostics_client/api/events_api.py
smart_diagnostics_client/api/files_api.py
smart_diagnostics_client/api/filters_api.py
smart_diagnostics_client/api/groups_api.py
smart_diagnostics_client/api/hardware_events_api.py
smart_diagnostics_client/api/hardware_status_api.py
smart_diagnostics_client/api/hubs_api.py
smart_diagnostics_client/api/identity_providers_api.py
smart_diagnostics_client/api/indicator_groups_api.py
smart_diagnostics_client/api/indicators_api.py
smart_diagnostics_client/api/installs_api.py
smart_diagnostics_client/api/locations_api.py
smart_diagnostics_client/api/markers_api.py
smart_diagnostics_client/api/monitoring_point_type_codes_api.py
smart_diagnostics_client/api/monitoring_points_api.py
smart_diagnostics_client/api/nodes_api.py
smart_diagnostics_client/api/pictures_api.py
smart_diagnostics_client/api/properties_api.py
smart_diagnostics_client/api/receivers_api.py
smart_diagnostics_client/api/repeaters_api.py
smart_diagnostics_client/api/reports_api.py
smart_diagnostics_client/api/scheduled_report_subscription_api.py
smart_diagnostics_client/api/sensors_api.py
smart_diagnostics_client/api/sessions_api.py
smartdiagnostics_sdk-3.31.0.dist-info/LICENSE
smartdiagnostics_sdk-3.31.0.dist-info/METADATA
smartdiagnostics_sdk-3.31.0.dist-info/WHEEL
smartdiagnostics_sdk-3.31.0.dist-info/top_level.txt
smartdiagnostics_sdk-3.31.0.dist-info/RECORD
