Metadata-Version: 2.1
Name: smartdiagnostics-sdk
Version: 3.31.0
Summary: Python SDK for executing the SMARTdiagnostics API
Home-page: http://www.kcftech.com
Author: KCF Technologies, Inc
Author-email: python-packages@kcftech.com
License: UNKNOWN
Platform: UNKNOWN
Classifier: Programming Language :: Python :: 3
Classifier: Operating System :: OS Independent
Requires-Python: >=3.6
